ctm.py
git_ctm-0.2.0.dist-info/DESCRIPTION.rst
git_ctm-0.2.0.dist-info/METADATA
git_ctm-0.2.0.dist-info/RECORD
git_ctm-0.2.0.dist-info/WHEEL
git_ctm-0.2.0.dist-info/entry_points.txt
git_ctm-0.2.0.dist-info/metadata.json
git_ctm-0.2.0.dist-info/top_level.txt
